AUTHORS.rst
CONTRIBUTING.rst
LICENSE
MANIFEST.in
README.rst
VERSION
setup.cfg
setup.py
bin/downtoearth-cli.py
docs/Makefile
docs/authors.rst
docs/conf.py
docs/contributing.rst
docs/downtoearth.rst
docs/index.rst
docs/installation.rst
docs/modules.rst
docs/readme.rst
docs/usage.rst
downtoearth/__init__.py
downtoearth/cli.py
downtoearth/default.py
downtoearth/exceptions.py
downtoearth/model.py
downtoearth/router.py
downtoearth/version.py
downtoearth.egg-info/PKG-INFO
downtoearth.egg-info/SOURCES.txt
downtoearth.egg-info/dependency_links.txt
downtoearth.egg-info/entry_points.txt
downtoearth.egg-info/requires.txt
downtoearth.egg-info/top_level.txt
downtoearth/templates/api_endpoints.hcl
downtoearth/templates/lambda.hcl
downtoearth/templates/policy.hcl
downtoearth/templates/root.hcl
tests/api.json
tests/test_downtoearth.py
tests/test_api/Makefile
tests/test_api/lambda_handler.py
tests/test_api/main.tf
tests/test_api/terraform.tfstate
tests/test_api/terraform.tfstate.backup