Metadata-Version: 1.0
Name: downtoearth
Version: 0.4.2
Summary: Utility to make API Gateway terraforms
Home-page: https://github.com/cleardataeng/downtoearth
Author: ClearDATA
Author-email: UNKNOWN
License: UNKNOWN
Platform: UNKNOWN
